zelll-0.3.0.dist-info/METADATA
zelll-0.3.0.dist-info/WHEEL
zelll.libs/libgcc_s-6d2d9dc8.so.1
zelll/__init__.py
zelll/__init__.pyi
zelll/py.typed
zelll/zelll.cpython-314t-x86_64-linux-musl.so
zelll-0.3.0.dist-info/RECORD
