Metadata-Version: 2.4
Name: zelll
Version: 0.3.0
Classifier: Programming Language :: Rust
Classifier: Programming Language :: Python :: Implementation :: CPython
Classifier: Programming Language :: Python :: Implementation :: PyPy
Summary: Python bindings for zelll.
Keywords: coarse-grained,molecular-dynamics,simulation,cell-lists
Author: Vincent Messow <vincent.messow@uni-jena.de>
Author-email: Vincent Messow <vincent.messow@uni-jena.de>
License: MIT
Requires-Python: >=3.8
Project-URL: repository, https://github.com/microscopic-image-analysis/zelll
Project-URL: documentation, https://microscopic-image-analysis.github.io/zelll
